{
  "enterprise_info": {
    "企业名称": "今麦郎",
    "统一社会信用代码": "871140",
    "企业类型": "有限责任公司",
    "所属行业": "食品",
    "注册资本（万元）": "13",
    "成立时间": "2013-05-16",
    "员工人数": "999",
    "年营业收入（万元）": "99",
    "联系人姓名": "降金龙",
    "联系人邮箱": "1990654288@qq.com",
    "联系人电话": "13663330239"
  },
  "answers": {
    "1": "不适用",
    "2": "否",
    "3": "否",
    "4": "一般",
    "5": "是",
    "6": "很有效",
    "7": "比较有效",
    "8": "比较有效",
    "9": "是",
    "10": "是",
    "11": "是",
    "12": "否",
    "13": "是",
    "16": "不太有效",
    "17": "是",
    "18": "是",
    "19": "很有效",
    "20": "很有效",
    "21": "否",
    "22": "否",
    "23": "是",
    "25": "否",
    "26": "是",
    "27": "否",
    "28": "是",
    "29": "是",
    "30": "否",
    "31": "很有效",
    "32": "比较有效",
    "229": "很有效",
    "230": "很有效",
    "231": "比较有效",
    "232": "不太有效",
    "233": "否",
    "234": "比较有效",
    "235": "不太有效"
  }
}